{
    "schools": [
        {
            "name": "北京邮电大学",
            "description": "北京邮电大学是教育部直属、工业和信息化部共建、首批进行“211工程”建设的全国重点大学，是“双一流”建设高校。学校拥有优良的教学科研环境，校园文化丰富，学术氛围浓厚，培养了众多优秀人才。",
            "location": "北京市海淀区西土城路10号（西土城路校区）；北京市昌平区沙河高教园区南三街（沙河校区）",
            "coordinates": {
                "latitude": 39.96343,
                "longitude": 116.35839
            },
            "rating": 4.70,
            "popularity": 80,
            "tags": [
                "高等学府",
                "学术研究",
                "校园观光"
            ],
            "price_range": "免费",
            "open_hours": {
                "weekday": "全天开放（部分教学区域除外）",
                "weekend": "全天开放（部分教学区域除外）"
            },
            "url": "https://images.pexels.com/photos/16141675/pexels-photo-16141675.jpeg?auto=compress&cs=tinysrgb&w=1260&h=750&dpr=2"
        },
        {
            "name": "北京师范大学",
            "description": "北京师范大学是教育部直属重点大学，是一所以教师教育、教育科学和文理基础学科为主要特色的著名学府，位列“双一流”、“985工程”、“211工程”。校园环境优美，文化底蕴深厚，拥有众多历史建筑和人文景观，是莘莘学子求学和游客感受学术氛围的好去处。",
            "location": "北京市海淀区新街口外大街19号（校本部）；北京市昌平区沙河高教园区南三街（昌平校区）",
            "coordinates": {
                "latitude": 39.96718,
                "longitude": 116.35077
            },
            "rating": 4.80,
            "popularity": 85,
            "tags": [
                "高等学府",
                "教育科研",
                "校园风光"
            ],
            "price_range": "免费",
            "open_hours": {
                "weekday": "全天（部分区域有时间限制）",
                "weekend": "全天（部分区域有时间限制）"
            },
            "url": "https://images.pexels.com/photos/16141675/pexels-photo-16141675.jpeg?auto=compress&cs=tinysrgb&w=1260&h=750&dpr=2"
        },
        {
            "name": "清华大学",
            "description": "清华大学是中华人民共和国教育部直属的全国重点大学，位列国家“双一流”A类、“985工程”、“211工程”，被誉为“红色工程师的摇篮”。校园景色优美，有众多知名建筑和景观。",
            "location": "北京市海淀区清华园1号",
            "coordinates": {
                "latitude": 39.99047,
                "longitude": 116.33732
            },
            "rating": 4.85,
            "popularity": 90,
            "tags": [
                "高等学府",
                "学术研究",
                "校园观光"
            ],
            "price_range": "免费",
            "open_hours": {
                "weekday": "需提前预约，按照预约时间进入（部分区域限制开放）",
                "weekend": "需提前预约，按照预约时间进入（部分区域限制开放）"
            },
            "url": "https://images.pexels.com/photos/16141675/pexels-photo-16141675.jpeg?auto=compress&cs=tinysrgb&w=1260&h=750&dpr=2"
        },
        {
            "name": "北京大学",
            "description": "北京大学是中华人民共和国教育部直属的全国重点大学，位列“双一流”、“211工程”、“985工程”，是新文化运动的中心和五四运动的策源地。校园环境典雅，充满人文气息。",
            "location": "北京市海淀区颐和园路5号",
            "coordinates": {
                "latitude": 39.99232,
                "longitude": 116.31985
            },
            "rating": 4.82,
            "popularity": 88,
            "tags": [
                "高等学府",
                "学术研究",
                "校园观光"
            ],
            "price_range": "免费",
            "open_hours": {
                "weekday": "需提前预约，按照预约时间进入（部分区域限制开放）",
                "weekend": "需提前预约，按照预约时间进入（部分区域限制开放）"
            },
            "url": "https://images.pexels.com/photos/16141675/pexels-photo-16141675.jpeg?auto=compress&cs=tinysrgb&w=1260&h=750&dpr=2"
        },
        {
            "name": "中国科学院大学",
            "description": "中国科学院大学是一所以科教融合为办学模式、研究生教育为办学主体的创新型大学，是国家“双一流”建设高校。学校在科研和学术方面具有很强的实力。",
            "location": "北京市怀柔区雁栖湖东路1号（雁栖湖校区）；北京市石景山区玉泉路19号（玉泉路校区）",
            "coordinates": {
                "latitude": 40.45132,
                "longitude": 116.62787
            },
            "rating": 4.75,
            "popularity": 82,
            "tags": [
                "高等学府",
                "科研创新",
                "学术交流"
            ],
            "price_range": "免费",
            "open_hours": {
                "weekday": "部分区域可参观，需遵循学校管理规定",
                "weekend": "部分区域可参观，需遵循学校管理规定"
            },
            "url": "https://images.pexels.com/photos/16141675/pexels-photo-16141675.jpeg?auto=compress&cs=tinysrgb&w=1260&h=750&dpr=2"
        },
        {
            "name": "北京航空航天大学",
            "description": "北京航空航天大学是中华人民共和国工业和信息化部直属的全国重点大学，位列“双一流”、“985工程”、“211工程”，在航空航天领域学科优势明显。",
            "location": "北京市海淀区学院路37号",
            "coordinates": {
                "latitude": 39.96534,
                "longitude": 116.35318
            },
            "rating": 4.78,
            "popularity": 83,
            "tags": [
                "高等学府",
                "航空航天",
                "学术研究"
            ],
            "price_range": "免费",
            "open_hours": {
                "weekday": "部分区域开放，需遵守学校相关规定",
                "weekend": "部分区域开放，需遵守学校相关规定"
            },
            "url": "https://images.pexels.com/photos/16141675/pexels-photo-16141675.jpeg?auto=compress&cs=tinysrgb&w=1260&h=750&dpr=2"
        },
        {
            "name": "北京理工大学",
            "description": "北京理工大学是中华人民共和国工业和信息化部直属的全国重点大学，位列“双一流”、“985工程”、“211工程”，兵器科学与技术、材料科学与工程等学科实力强劲。",
            "location": "北京市海淀区中关村南大街5号",
            "coordinates": {
                "latitude": 39.94983,
                "longitude": 116.34133
            },
            "rating": 4.76,
            "popularity": 81,
            "tags": [
                "高等学府",
                "兵器军工",
                "学术研究"
            ],
            "price_range": "免费",
            "open_hours": {
                "weekday": "部分区域可进入，需遵循校内指引",
                "weekend": "部分区域可进入，需遵循校内指引"
            },
            "url": "https://images.pexels.com/photos/16141675/pexels-photo-16141675.jpeg?auto=compress&cs=tinysrgb&w=1260&h=750&dpr=2"
        },
        {
            "name": "复旦大学",
            "description": "复旦大学是教育部直属、中央直管副部级建制的全国重点大学，是国家“双一流”、“985工程”、“211工程”建设高校，在人文社科、自然科学等多领域实力强劲。校园充满人文气息和学术氛围。",
            "location": "上海市杨浦区邯郸路220号（邯郸校区）等多个校区",
            "coordinates": {
                "latitude": 31.29974,
                "longitude": 121.50939
            },
            "rating": 4.82,
            "popularity": 88,
            "tags": [
                "高等学府",
                "学术研究",
                "校园观光"
            ],
            "price_range": "免费",
            "open_hours": {
                "weekday": "部分区域开放，需遵守学校管理规定",
                "weekend": "部分区域开放，需遵守学校管理规定"
            },
            "url": "https://images.pexels.com/photos/16141675/pexels-photo-16141675.jpeg?auto=compress&cs=tinysrgb&w=1260&h=750&dpr=2"
        },
        {
            "name": "浙江大学",
            "description": "浙江大学是教育部直属的综合性全国重点大学，是国家“双一流”、“985工程”、“211工程”建设高校，学科门类齐全，科研实力雄厚。校园环境优美，景色宜人。",
            "location": "浙江省杭州市西湖区余杭塘路866号（紫金港校区）等多个校区",
            "coordinates": {
                "latitude": 30.29238,
                "longitude": 120.12964
            },
            "rating": 4.85,
            "popularity": 90,
            "tags": [
                "高等学府",
                "学术研究",
                "校园风光"
            ],
            "price_range": "免费",
            "open_hours": {
                "weekday": "部分区域按规定开放",
                "weekend": "部分区域按规定开放"
            },
            "url": "https://images.pexels.com/photos/16141675/pexels-photo-16141675.jpeg?auto=compress&cs=tinysrgb&w=1260&h=750&dpr=2"
        },
        {
            "name": "上海交通大学",
            "description": "上海交通大学是教育部直属并与上海市共建的全国重点大学，是国家“双一流”、“985工程”、“211工程”建设高校，在工科、医科等领域优势突出。校园具有深厚的历史文化底蕴。",
            "location": "上海市闵行区东川路800号（闵行校区）等多个校区",
            "coordinates": {
                "latitude": 31.02774,
                "longitude": 121.43747
            },
            "rating": 4.83,
            "popularity": 89,
            "tags": [
                "高等学府",
                "学术研究",
                "校园游览"
            ],
            "price_range": "免费",
            "open_hours": {
                "weekday": "部分区域开放，需预约或遵循规定",
                "weekend": "部分区域开放，需预约或遵循规定"
            },
            "url": "https://images.pexels.com/photos/16141675/pexels-photo-16141675.jpeg?auto=compress&cs=tinysrgb&w=1260&h=750&dpr=2"
        },
        {
            "name": "南京大学",
            "description": "南京大学是教育部直属的全国重点大学，是国家“双一流”、“985工程”、“211工程”建设高校，学科优势明显，科研成果丰硕。校园建筑风格独特，文化氛围浓郁。",
            "location": "江苏省南京市栖霞区仙林大道163号（仙林校区）等多个校区",
            "coordinates": {
                "latitude": 32.11643,
                "longitude": 118.91618
            },
            "rating": 4.80,
            "popularity": 87,
            "tags": [
                "高等学府",
                "学术研究",
                "历史文化"
            ],
            "price_range": "免费",
            "open_hours": {
                "weekday": "部分区域开放，遵守校内要求",
                "weekend": "部分区域开放，遵守校内要求"
            },
            "url": "https://images.pexels.com/photos/16141675/pexels-photo-16141675.jpeg?auto=compress&cs=tinysrgb&w=1260&h=750&dpr=2"
        },
        {
            "name": "华中科技大学",
            "description": "华中科技大学是教育部直属的综合性研究型全国重点大学，是国家“双一流”、“985工程”、“211工程”建设高校，在医学、工科等方面表现卓越。校园面积大，风景优美。",
            "location": "湖北省武汉市洪山区珞喻路1037号",
            "coordinates": {
                "latitude": 30.51420,
                "longitude": 114.40026
            },
            "rating": 4.78,
            "popularity": 85,
            "tags": [
                "高等学府",
                "学术研究",
                "校园景观"
            ],
            "price_range": "免费",
            "open_hours": {
                "weekday": "部分区域开放，按学校规定执行",
                "weekend": "部分区域开放，按学校规定执行"
            },
            "url": "https://images.pexels.com/photos/16141675/pexels-photo-16141675.jpeg?auto=compress&cs=tinysrgb&w=1260&h=750&dpr=2"
        },
        {
            "name": "中国科学技术大学",
            "description": "中国科学技术大学是中国科学院直属的一所以前沿科学和高新技术为主，兼有医学、特色管理和人文学科的综合性全国重点大学，是国家“双一流”、“985工程”、“211工程”建设高校，科研实力顶尖。校园充满浓厚的学术氛围。",
            "location": "安徽省合肥市包河区金寨路96号（东区）等多个校区",
            "coordinates": {
                "latitude": 31.83095,
                "longitude": 117.22951
            },
            "rating": 4.75,
            "popularity": 83,
            "tags": [
                "高等学府",
                "科研创新",
                "学术交流"
            ],
            "price_range": "免费",
            "open_hours": {
                "weekday": "部分区域可参观，遵循学校管理",
                "weekend": "部分区域可参观，遵循学校管理"
            },
            "url": "https://images.pexels.com/photos/16141675/pexels-photo-16141675.jpeg?auto=compress&cs=tinysrgb&w=1260&h=750&dpr=2"
        },
        {
            "name": "中国人民大学",
            "description": "中国人民大学是教育部直属高校，是国家“双一流”建设高校、“211工程”“985工程”重点建设高校。学校在人文社会科学领域具有突出优势，拥有深厚的学术底蕴和优良的学风。校园充满人文气息，建筑风格庄重典雅。",
            "location": "北京市海淀区中关村大街59号",
            "coordinates": {
                "latitude": 39.95022,
                "longitude": 116.30773
            },
            "rating": 4.80,
            "popularity": 86,
            "tags": [
                "高等学府",
                "人文社科",
                "校园文化"
            ],
            "price_range": "免费",
            "open_hours": {
                "weekday": "部分区域开放，需遵守学校规定",
                "weekend": "部分区域开放，需遵守学校规定"
            },
            "url": "https://images.pexels.com/photos/16141675/pexels-photo-16141675.jpeg?auto=compress&cs=tinysrgb&w=1260&h=750&dpr=2"
        },
        {
            "name": "天津大学",
            "description": "天津大学是教育部直属全国重点大学，是国家“双一流”建设高校、“211工程”“985工程”重点建设高校。其工科实力强劲，历史悠久，是中国第一所现代大学。校园内有众多具有历史意义的建筑和景观。",
            "location": "天津市南开区卫津路92号",
            "coordinates": {
                "latitude": 39.08224,
                "longitude": 117.19917
            },
            "rating": 4.78,
            "popularity": 84,
            "tags": [
                "高等学府",
                "工科强校",
                "历史建筑"
            ],
            "price_range": "免费",
            "open_hours": {
                "weekday": "部分区域开放，遵循校内指引",
                "weekend": "部分区域开放，遵循校内指引"
            },
            "url": "https://images.pexels.com/photos/16141675/pexels-photo-16141675.jpeg?auto=compress&cs=tinysrgb&w=1260&h=750&dpr=2"
        },
        {
            "name": "南开大学",
            "description": "南开大学由严修、张伯苓秉承教育救国理念创办，是教育部直属重点综合性大学，国家“双一流”建设高校、“211工程”“985工程”重点建设高校。学科门类齐全，在多个学科领域取得了卓越成就。校园环境优美，文化氛围浓厚。",
            "location": "天津市南开区津南校区同砚路38号等多个校区",
            "coordinates": {
                "latitude": 38.97227,
                "longitude": 117.33105
            },
            "rating": 4.82,
            "popularity": 87,
            "tags": [
                "高等学府",
                "学科多样",
                "校园风光"
            ],
            "price_range": "免费",
            "open_hours": {
                "weekday": "部分区域开放，按学校要求进入",
                "weekend": "部分区域开放，按学校要求进入"
            },
            "url": "https://images.pexels.com/photos/16141675/pexels-photo-16141675.jpeg?auto=compress&cs=tinysrgb&w=1260&h=750&dpr=2"
        },
        {
            "name": "武汉大学",
            "description": "武汉大学是教育部直属重点综合性大学，是国家“双一流”建设高校、“211工程”“985工程”重点建设高校。学校坐拥珞珈山，环绕东湖水，校园环境优美，建筑风格独特，被誉为“中国最美丽的大学”之一。学科门类丰富，学术氛围浓厚。",
            "location": "湖北省武汉市武昌区八一路299号",
            "coordinates": {
                "latitude": 30.52992,
                "longitude": 114.35701
            },
            "rating": 4.90,
            "popularity": 92,
            "tags": [
                "高等学府",
                "校园美景",
                "樱花胜地"
            ],
            "price_range": "免费（樱花季可能需预约）",
            "open_hours": {
                "weekday": "部分区域开放，遵守校内管理",
                "weekend": "部分区域开放，遵守校内管理"
            },
            "url": "https://images.pexels.com/photos/16141675/pexels-photo-16141675.jpeg?auto=compress&cs=tinysrgb&w=1260&h=750&dpr=2"
        },
        {
            "name": "中山大学",
            "description": "中山大学是教育部直属高校，是国家“双一流”建设高校、“211工程”“985工程”重点建设高校。学科实力强劲，在医学、文科、理科等多个领域都有出色表现。校园具有深厚的历史文化底蕴和独特的岭南风情。",
            "location": "广东省广州市新港西路135号（南校区）等多个校区",
            "coordinates": {
                "latitude": 23.05837,
                "longitude": 113.39432
            },
            "rating": 4.85,
            "popularity": 89,
            "tags": [
                "高等学府",
                "学科优势",
                "岭南文化"
            ],
            "price_range": "免费",
            "open_hours": {
                "weekday": "部分区域开放，遵循学校规定",
                "weekend": "部分区域开放，遵循学校规定"
            },
            "url": "https://images.pexels.com/photos/16141675/pexels-photo-16141675.jpeg?auto=compress&cs=tinysrgb&w=1260&h=750&dpr=2"
        },
        {
            "name": "四川大学",
            "description": "四川大学是教育部直属全国重点大学，是国家布局在中国西部的重点建设的高水平研究型综合大学，也是国家“双一流”建设高校（A类）、国家“211工程”和“985工程”重点建设的高校之一。学科门类齐全，覆盖了文、理、工、医、经、管、法、史、哲、农、教、艺等12个门类。校园历史文化底蕴深厚。",
            "location": "四川省成都市武侯区一环路南一段24号（望江校区）等多个校区",
            "coordinates": {
                "latitude": 30.62582,
                "longitude": 104.08873
            },
            "rating": 4.83,
            "popularity": 88,
            "tags": [
                "高等学府",
                "综合学科",
                "校园文化"
            ],
            "price_range": "免费",
            "open_hours": {
                "weekday": "部分区域开放，遵循学校管理规定",
                "weekend": "部分区域开放，遵循学校管理规定"
            },
            "url": "https://images.pexels.com/photos/16141675/pexels-photo-16141675.jpeg?auto=compress&cs=tinysrgb&w=1260&h=750&dpr=2"
        },
        {
            "name": "吉林大学",
            "description": "吉林大学是教育部直属的全国重点综合性大学，是国家“双一流”建设高校、国家“211工程”和“985工程”重点建设的大学之一。学科门类十分齐全，涵盖了哲学、经济学、法学、教育学、文学、历史学等多个学科门类。学校规模宏大。",
            "location": "吉林省长春市前进大街2699号（前卫南区）等多个校区",
            "coordinates": {
                "latitude": 43.82503,
                "longitude": 125.24434
            },
            "rating": 4.78,
            "popularity": 85,
            "tags": [
                "高等学府",
                "多学科融合",
                "校园风貌"
            ],
            "price_range": "免费",
            "open_hours": {
                "weekday": "部分区域开放，遵守校内制度",
                "weekend": "部分区域开放，遵守校内制度"
            },
            "url": "https://images.pexels.com/photos/16141675/pexels-photo-16141675.jpeg?auto=compress&cs=tinysrgb&w=1260&h=750&dpr=2"
        },
        {
            "name": "山东大学",
            "description": "山东大学是教育部直属全国重点大学，是国家“双一流”建设高校（A类）、国家“211工程”和“985工程”重点建设的大学之一。学科门类齐全，在文史哲、数学、物理、化学、医学等学科领域具有雄厚的学科实力和鲜明的特色。",
            "location": "山东省济南市历城区山大南路27号（中心校区）等多个校区",
            "coordinates": {
                "latitude": 36.66240,
                "longitude": 117.06833
            },
            "rating": 4.80,
            "popularity": 86,
            "tags": [
                "高等学府",
                "学科优势",
                "校园氛围"
            ],
            "price_range": "免费",
            "open_hours": {
                "weekday": "部分区域开放，按学校指引进入",
                "weekend": "部分区域开放，按学校指引进入"
            },
            "url": "https://images.pexels.com/photos/16141675/pexels-photo-16141675.jpeg?auto=compress&cs=tinysrgb&w=1260&h=750&dpr=2"
        },
        {
            "name": "厦门大学",
            "description": "厦门大学是教育部直属的综合性研究型全国重点大学，是国家“双一流”建设高校、国家“211工程”和“985工程”重点建设高校。校园背山面海，风景秀丽，建筑风格独特，被誉为“中国最美大学”之一。学科涵盖了文、理、工、商、法、医等多个学科领域。",
            "location": "福建省厦门市思明区思明南路422号",
            "coordinates": {
                "latitude": 24.44595,
                "longitude": 118.08741
            },
            "rating": 4.92,
            "popularity": 93,
            "tags": [
                "高等学府",
                "海滨校园",
                "旅游胜地"
            ],
            "price_range": "免费（需预约，特定时段可能限流）",
            "open_hours": {
                "weekday": "按预约时间和学校规定开放部分区域",
                "weekend": "按预约时间和学校规定开放部分区域"
            },
            "url": "https://images.pexels.com/photos/16141675/pexels-photo-16141675.jpeg?auto=compress&cs=tinysrgb&w=1260&h=750&dpr=2"
        },
        {
            "name": "同济大学",
            "description": "同济大学是教育部直属并与上海市共建的全国重点大学，是国家“双一流”建设高校、国家“211工程”和“985工程”重点建设高校。在建筑、土木、交通等学科领域处于国内领先地位。校园充满了浓厚的学术氛围和独特的文化气息。",
            "location": "上海市杨浦区四平路1239号",
            "coordinates": {
                "latitude": 31.29837,
                "longitude": 121.50903
            },
            "rating": 4.85,
            "popularity": 89,
            "tags": [
                "高等学府",
                "工科优势",
                "校园建筑"
            ],
            "price_range": "免费",
            "open_hours": {
                "weekday": "部分区域开放，遵循校内要求",
                "weekend": "部分区域开放，遵循校内要求"
            },
            "url": "https://images.pexels.com/photos/16141675/pexels-photo-16141675.jpeg?auto=compress&cs=tinysrgb&w=1260&h=750&dpr=2"
        },
        {
            "name": "中南大学",
            "description": "中南大学是教育部直属全国重点大学，是国家“双一流”建设高校、国家“211工程”和“985工程”重点建设高校。在材料科学、冶金工程、矿业工程、临床医学等学科领域具有显著优势。校园环境优美，学术氛围浓厚。",
            "location": "湖南省长沙市岳麓区麓山南路932号",
            "coordinates": {
                "latitude": 28.17733,
                "longitude": 112.93005
            },
            "rating": 4.81,
            "popularity": 87,
            "tags": [
                "高等学府",
                "优势学科",
                "校园风光"
            ],
            "price_range": "免费",
            "open_hours": {
                "weekday": "部分区域开放，遵守学校管理",
                "weekend": "部分区域开放，遵守学校管理"
            },
            "url": "https://images.pexels.com/photos/16141675/pexels-photo-16141675.jpeg?auto=compress&cs=tinysrgb&w=1260&h=750&dpr=2"
        }
    ],
    "scenic_spots": [
        {
            "name": "故宫博物院",
            "description": "中国明清两代的皇家宫殿，是世界上现存规模最大、保存最为完整的木质结构古建筑群之一，承载着丰富的历史文化内涵，拥有大量的文物珍宝。",
            "location": "北京市东城区景山前街4号",
            "coordinates": {
                "latitude": 39.91634,
                "longitude": 116.39712
            },
            "rating": 4.90,
            "popularity": 98,
            "tags": [
                "博物馆",
                "古建筑",
                "历史文化",
                "亲子游",
                "人文景观"
            ],
            "price_range": "¥40-60",
            "open_hours": {
                "weekday": "8:30-17:00",
                "weekend": "8:30-17:00"
            },
            "url": "https://images.pexels.com/photos/16141675/pexels-photo-16141675.jpeg?auto=compress&cs=tinysrgb&w=1260&h=750&dpr=2"
        },
        {
            "name": "天安门广场",
            "description": "世界上最大的城市广场之一，是中国的象征之一，是举行重大庆典、盛大集会和外事迎宾的神圣重地，周边有人民英雄纪念碑、毛主席纪念堂等重要建筑。",
            "location": "北京市东城区东长安街",
            "coordinates": {
                "latitude": 39.90882,
                "longitude": 116.39741
            },
            "rating": 4.90,
            "popularity": 99,
            "tags": [
                "广场",
                "爱国主义教育基地",
                "人文景观",
                "城市地标"
            ],
            "price_range": "免费",
            "open_hours": {
                "weekday": "全天开放",
                "weekend": "全天开放"
            },
            "url": "https://images.pexels.com/photos/31427555/pexels-photo-31427555.jpeg?auto=compress&cs=tinysrgb&w=1260&h=750&dpr=2"
        },
        {
            "name": "八达岭长城",
            "description": "万里长城的重要组成部分，是明长城的一个隘口，地势险要，山峦重叠，形势险要，是居庸关的重要前哨。",
            "location": "北京市延庆区军都山关沟古道北口",
            "coordinates": {
                "latitude": 40.39632,
                "longitude": 116.02724
            },
            "rating": 4.80,
            "popularity": 97,
            "tags": [
                "长城",
                "历史遗迹",
                "户外运动",
                "自然风光",
                "人文景观"
            ],
            "price_range": "¥35-40",
            "open_hours": {
                "weekday": "6:30-16:30",
                "weekend": "6:00-17:00"
            },
            "url": "https://images.pexels.com/photos/31639350/pexels-photo-31639350.jpeg?auto=compress&cs=tinysrgb&w=1260&h=750&dpr=2"
        },
        {
            "name": "颐和园",
            "description": "大型皇家园林，也是保存最完整的一座皇家行宫御苑，被誉为“皇家园林博物馆”，汲取江南园林的设计手法而建，有湖光山色、长廊、佛香阁等众多景观。",
            "location": "北京市海淀区新建宫门路19号",
            "coordinates": {
                "latitude": 39.99472,
                "longitude": 116.26000
            },
            "rating": 4.80,
            "popularity": 96,
            "tags": [
                "皇家园林",
                "古建筑",
                "自然风光",
                "亲子游",
                "人文景观"
            ],
            "price_range": "¥20-60",
            "open_hours": {
                "weekday": "6:30-18:00",
                "weekend": "6:30-18:00"
            },
            "url": "https://images.pexels.com/photos/9168181/pexels-photo-9168181.jpeg?auto=compress&cs=tinysrgb&w=1260&h=750&dpr=2"
        },
        {
            "name": "兵马俑",
            "description": "秦始皇陵的陪葬坑，是世界考古史上最伟大的发现之一，规模宏大，陶俑形象栩栩如生，展示了秦朝的军事、文化和艺术成就。",
            "location": "陕西省西安市临潼区秦陵北路",
            "coordinates": {
                "latitude": 34.38520,
                "longitude": 109.27332
            },
            "rating": 4.80,
            "popularity": 97,
            "tags": [
                "历史遗迹",
                "博物馆",
                "人文景观",
                "历史文化"
            ],
            "price_range": "¥120",
            "open_hours": {
                "weekday": "8:30-17:00",
                "weekend": "8:30-17:00"
            },
            "url": "https://images.pexels.com/photos/26741550/pexels-photo-26741550.jpeg?auto=compress&cs=tinysrgb&w=1260&h=750&dpr=2"
        },
        {
            "name": "东方明珠塔",
            "description": "上海的标志性文化景观之一，集都市观光、时尚餐饮、购物娱乐、历史陈列、浦江游览、会展演出等多功能于一体，可俯瞰上海城市风光。",
            "location": "上海市浦东新区世纪大道1号",
            "coordinates": {
                "latitude": 31.23971,
                "longitude": 121.49917
            },
            "rating": 4.70,
            "popularity": 95,
            "tags": [
                "城市地标",
                "观光塔",
                "旅游景点",
                "夜景"
            ],
            "price_range": "¥100-220",
            "open_hours": {
                "weekday": "9:00-21:30",
                "weekend": "9:00-21:30"
            },
            "url": "https://images.pexels.com/photos/9157204/pexels-photo-9157204.jpeg?auto=compress&cs=tinysrgb&w=1260&h=750&dpr=2"
        },
        {
            "name": "上海迪士尼乐园",
            "description": "中国内地首座迪士尼主题乐园，拥有七大主题园区、众多游乐项目、精彩的演艺活动和丰富的餐饮购物选择，充满欢乐和梦幻氛围。",
            "location": "上海市浦东新区川沙新镇上海迪士尼度假区",
            "coordinates": {
                "latitude": 31.14332,
                "longitude": 121.65696
            },
            "rating": 4.80,
            "popularity": 98,
            "tags": [
                "主题公园",
                "亲子游",
                "娱乐休闲",
                "童话世界"
            ],
            "price_range": "¥399-799",
            "open_hours": {
                "weekday": "根据季节调整",
                "weekend": "根据季节调整"
            },
            "url": "https://images.pexels.com/photos/3411135/pexels-photo-3411135.jpeg?auto=compress&cs=tinysrgb&w=1260&h=750&dpr=2"
        },
        {
            "name": "外滩",
            "description": "上海最具代表性的景点之一，位于黄浦江畔，矗立着52幢风格迥异的古典复兴大楼，有“万国建筑博览群”之称，可欣赏到黄浦江两岸的繁华景象。",
            "location": "上海市黄浦区中山东一路",
            "coordinates": {
                "latitude": 31.24189,
                "longitude": 121.49216
            },
            "rating": 4.80,
            "popularity": 99,
            "tags": [
                "城市风光",
                "历史建筑",
                "夜景",
                "旅游打卡地"
            ],
            "price_range": "免费",
            "open_hours": {
                "weekday": "全天开放",
                "weekend": "全天开放"
            },
            "url": "https://images.pexels.com/photos/30685872/pexels-photo-30685872.jpeg?auto=compress&cs=tinysrgb&w=1260&h=750&dpr=2"
        },
        {
            "name": "黄山风景区",
            "description": "世界文化与自然双重遗产，以奇松、怪石、云海、温泉“四绝”闻名于世，有“五岳归来不看山，黄山归来不看岳”之名，风景秀丽，景色壮观。",
            "location": "安徽省黄山市黄山区汤口镇",
            "coordinates": {
                "latitude": 30.15237,
                "longitude": 118.17911
            },
            "rating": 4.80,
            "popularity": 96,
            "tags": [
                "自然风光",
                "山岳景观",
                "户外运动",
                "旅游胜地"
            ],
            "price_range": "¥150-190",
            "open_hours": {
                "weekday": "6:30-17:00",
                "weekend": "6:00-17:30"
            },
            "url": "https://images.pexels.com/photos/12453895/pexels-photo-12453895.png?auto=compress&cs=tinysrgb&w=1260&h=750&dpr=2"
        },
        {
            "name": "九寨沟",
            "description": "世界自然遗产，以有九个藏族村寨而得名。有碧绿的湖水、壮观的瀑布群、雪峰林立的高山等自然景观，景色如诗如画，四季各异。",
            "location": "四川省阿坝藏族羌族自治州九寨沟县漳扎镇",
            "coordinates": {
                "latitude": 33.19928,
                "longitude": 103.85348
            },
            "rating": 4.90,
            "popularity": 97,
            "tags": [
                "自然风光",
                "湖泊",
                "瀑布",
                "森林",
                "旅游胜地"
            ],
            "price_range": "旺季（4月1日-11月15日）：门票169元，观光车票90元；淡季（11月16日-次年3月31日）：门票80元，观光车票80元",
            "open_hours": {
                "weekday": "7:30-17:00",
                "weekend": "7:30-17:00"
            },
            "url": "https://images.pexels.com/photos/8370819/pexels-photo-8370819.jpeg?auto=compress&cs=tinysrgb&w=1260&h=750&dpr=2"
        },
        {
            "name": "张家界国家森林公园",
            "description": "中国第一个国家森林公园，奇峰异石林立，有三千奇峰，八百秀水之美称，是电影《阿凡达》中“哈利路亚山”的原型取景地。",
            "location": "湖南省张家界市武陵源区金鞭路279号",
            "coordinates": {
                "latitude": 29.23997,
                "longitude": 110.47941
            },
            "rating": 4.80,
            "popularity": 96,
            "tags": [
                "自然风光",
                "山岳景观",
                "森林",
                "户外运动",
                "旅游景区"
            ],
            "price_range": "旺季（3月1日-11月30日）：228元（含环保车票价）；淡季（12月1日-次年2月底）：115元（含环保车票价）",
            "open_hours": {
                "weekday": "7:00-18:00",
                "weekend": "7:00-18:00"
            },
            "url": "https://images.pexels.com/photos/25000725/pexels-photo-25000725.jpeg?auto=compress&cs=tinysrgb&w=1260&h=750&dpr=2"
        },
        {
            "name": "西湖",
            "description": "中国十大风景名胜之一，三面云山，中涵碧水，湖光山色相互映衬，有断桥残雪、雷峰夕照、三潭印月等众多著名景点，文化底蕴深厚。",
            "location": "浙江省杭州市西湖区龙井路1号",
            "coordinates": {
                "latitude": 30.24900,
                "longitude": 120.15459
            },
            "rating": 4.90,
            "popularity": 98,
            "tags": [
                "自然风光",
                "湖泊",
                "历史文化",
                "旅游胜地",
                "人文景观"
            ],
            "price_range": "大部分免费，部分景点如灵隐寺等单独收费",
            "open_hours": {
                "weekday": "全天开放",
                "weekend": "全天开放"
            },
            "url": "https://images.pexels.com/photos/7532194/pexels-photo-7532194.jpeg?auto=compress&cs=tinysrgb&w=1260&h=750&dpr=2"
        },
        {
            "name": "南京夫子庙",
            "description": "一组规模宏大的古建筑群，主要由孔庙、学宫、贡院三大建筑群组成，是中国第一所国家最高学府，也是中国四大文庙之一，周边有秦淮河风光带。",
            "location": "江苏省南京市秦淮区夫子庙步行街",
            "coordinates": {
                "latitude": 32.02582,
                "longitude": 118.78797
            },
            "rating": 4.70,
            "popularity": 95,
            "tags": [
                "历史文化",
                "古建筑",
                "商业街",
                "旅游景点",
                "人文景观"
            ],
            "price_range": "夫子庙大成殿30元，江南贡院25元，王谢古居8元，李香君故居16元等",
            "open_hours": {
                "weekday": "各景点开放时间不同，一般9:00-21:00左右",
                "weekend": "各景点开放时间不同，一般9:00-21:00左右"
            },
            "url": "https://images.pexels.com/photos/14544939/pexels-photo-14544939.jpeg?auto=compress&cs=tinysrgb&w=1260&h=750&dpr=2"
        },
        {
            "name": "重庆洪崖洞",
            "description": "以巴渝传统建筑特色的“吊脚楼”风貌为主体，依山就势，沿江而建，夜晚灯光亮起，宛如千与千寻中的奇幻世界，是重庆的网红打卡地。",
            "location": "重庆市渝中区嘉陵江滨江路88号",
            "coordinates": {
                "latitude": 29.56591,
                "longitude": 106.56947
            },
            "rating": 4.70,
            "popularity": 96,
            "tags": [
                "古建筑",
                "夜景",
                "旅游打卡地",
                "城市风光"
            ],
            "price_range": "免费",
            "open_hours": {
                "weekday": "11:00-23:00",
                "weekend": "11:00-23:00"
            },
            "url": "https://images.pexels.com/photos/2875254/pexels-photo-2875254.jpeg?auto=compress&cs=tinysrgb&w=1260&h=750&dpr=2"
        },
        {
            "name": "成都宽窄巷子",
            "description": "由宽巷子、窄巷子和井巷子平行排列组成，是成都遗留下来的较成规模的清朝古街道，具有浓郁的成都风情，有许多特色小吃、茶馆和店铺。",
            "location": "四川省成都市青羊区长顺上街127号",
            "coordinates": {
                "latitude": 30.66691,
                "longitude": 104.06005
            },
            "rating": 4.70,
            "popularity": 95,
            "tags": [
                "历史文化",
                "商业街",
                "古建筑",
                "旅游景点",
                "人文景观"
            ],
            "price_range": "免费",
            "open_hours": {
                "weekday": "全天开放",
                "weekend": "全天开放"
            },
            "url": "https://media.istockphoto.com/id/2168685787/zh/%E7%85%A7%E7%89%87/snacks-in-kuanzhai-alley-chengdu-china.jpg?s=2048x2048&w=is&k=20&c=HEwfEvIOBZKi211hq9B2m1A5FW8P4G517Ix8CqumU7E="
        },
        {
            "name": "大雁塔",
            "description": "现存最早、规模最大的唐代四方楼阁式砖塔，是为保存玄奘法师由天竺经丝绸之路带回长安的经卷佛像而建，是西安的标志性建筑之一。",
            "location": "陕西省西安市雁塔区大慈恩寺内",
            "coordinates": {
                "latitude": 34.22253,
                "longitude": 108.94382
            },
            "rating": 4.70,
            "popularity": 95,
            "tags": [
                "历史文化",
                "古建筑",
                "佛教文化",
                "旅游景点",
                "人文景观"
            ],
            "price_range": "大慈恩寺门票40元，登塔30元",
            "open_hours": {
                "weekday": "8:00-18:30",
                "weekend": "8:00-18:30"
            },
            "url": "https://images.pexels.com/photos/13998387/pexels-photo-13998387.jpeg?auto=compress&cs=tinysrgb&w=1260&h=750&dpr=2"
        },
        {
            "name": "布达拉宫",
            "description": "世界上海拔最高，集宫殿、城堡和寺院于一体的宏伟建筑，也是西藏最庞大、最完整的古代宫堡建筑群，是藏传佛教的圣地。",
            "location": "西藏自治区拉萨市城关区北京中路35号",
            "coordinates": {
                "latitude": 29.65294,
                "longitude": 91.13642
            },
            "rating": 4.80,
            "popularity": 97,
            "tags": [
                "历史文化",
                "古建筑",
                "佛教文化",
                "旅游胜地",
                "人文景观"
            ],
            "price_range": "旺季（5月1日-10月31日）：200元；淡季（11月1日-次年4月30日）：100元",
            "open_hours": {
                "weekday": "9:00-12:00，15:30-16:30",
                "weekend": "9:00-12:00，15:30-16:30"
            },
            "url": "https://images.pexels.com/photos/8604523/pexels-photo-8604523.jpeg?auto=compress&cs=tinysrgb&w=1260&h=750&dpr=2"
        },
        {
            "name": "洱海",
            "description": "云南省第二大淡水湖，西面有点苍山横列如屏，东面有玉案山环绕衬托，空间环境优美，周边有双廊、喜洲等特色小镇。",
            "location": "云南省大理白族自治州大理市",
            "coordinates": {
                "latitude": 25.70745,
                "longitude": 100.18847
            },
            "rating": 4.80,
            "popularity": 96,
            "tags": [
                "自然风光",
                "湖泊",
                "旅游胜地",
                "休闲度假"
            ],
            "price_range": "免费，部分景点如南诏风情岛等单独收费",
            "open_hours": {
                "weekday": "全天开放",
                "weekend": "全天开放"
            },
            "url": "https://images.pexels.com/photos/31168964/pexels-photo-31168964.jpeg?auto=compress&cs=tinysrgb&w=1260&h=750&dpr=2"
        },
        {
            "name": "鼓浪屿",
            "description": "鼓浪屿是厦门西南禺的一座小岛，岛上气候宜人，四季如春，无车马喧嚣，有鸟语花香，素有“海上花园”之誉。岛上保存大量中外风格各异的建筑物，有“万国建筑博览”之称。",
            "location": "福建省厦门市思明区鼓浪屿",
            "coordinates": {
                "latitude": 24.43978,
                "longitude": 118.03732
            },
            "rating": 4.87,
            "popularity": 92,
            "tags": [
                "海岛",
                "历史建筑",
                "音乐之岛"
            ],
            "price_range": "上岛免费，部分景点单独收费，联票约 100 - 130 元",
            "open_hours": {
                "weekday": "全天开放",
                "weekend": "全天开放"
            },
            "url": "https://images.pexels.com/photos/31168964/pexels-photo-31168964.jpeg?auto=compress&cs=tinysrgb&w=1260&h=750&dpr=2"
        },
        {
            "name": "稻城亚丁",
            "description": "稻城亚丁主要由“仙乃日、央迈勇、夏诺多吉”三座神山和周围的河流、湖泊和高山草甸组成，它的景致保持着在地球上近绝迹的纯粹，因其独特的地貌和原生态的自然风光，被誉为“香格里拉之魂”和“最后的香格里拉”。",
            "location": "四川省甘孜藏族自治州稻城县香格里拉镇亚丁村境内",
            "coordinates": {
                "latitude": 28.39335,
                "longitude": 100.49242
            },
            "rating": 4.90,
            "popularity": 90,
            "tags": [
                "高原雪山",
                "自然保护区",
                "徒步胜地"
            ],
            "price_range": "门票 150 元，观光车 120 元",
            "open_hours": {
                "weekday": "07:00 - 17:30",
                "weekend": "07:00 - 17:30"
            },
            "url": "https://images.pexels.com/photos/31168964/pexels-photo-31168964.jpeg?auto=compress&cs=tinysrgb&w=1260&h=750&dpr=2"
        },
        {
            "name": "长江三峡",
            "description": "长江三峡是瞿塘峡、巫峡和西陵峡三段峡谷的总称，西起重庆市奉节县白帝城，东至湖北宜昌市南津关，全长 193 千米，沿途两岸奇峰陡立、峭壁对峙，自西向东依次为瞿塘峡、巫峡、西陵峡。",
            "location": "西起重庆市奉节县白帝城，东至湖北省宜昌市南津关",
            "coordinates": {
                "latitude": 30.94547,
                "longitude": 110.77173
            },
            "rating": 4.85,
            "popularity": 88,
            "tags": [
                "峡谷风光",
                "游船观光",
                "历史文化"
            ],
            "price_range": "游船票价因线路和船型而异，大致在 500 - 5000 元不等",
            "open_hours": {
                "weekday": "游船运营时间各不相同",
                "weekend": "游船运营时间各不相同"
            },
            "url": "https://images.pexels.com/photos/31168964/pexels-photo-31168964.jpeg?auto=compress&cs=tinysrgb&w=1260&h=750&dpr=2"
        },
        {
            "name": "苏州园林",
            "description": "苏州园林是世界文化遗产，主要有沧浪亭、狮子林、拙政园、留园、网师园、怡园等园林，以其精美的造园艺术和深厚的文化内涵闻名于世，体现了中国江南地区传统的园林建筑风格。",
            "location": "江苏省苏州市",
            "coordinates": {
                "latitude": 31.29882,
                "longitude": 120.58539
            },
            "rating": 4.88,
            "popularity": 91,
            "tags": [
                "古典园林",
                "江南水乡",
                "文化遗产"
            ],
            "price_range": "各园林票价不同，大致在 20 - 90 元",
            "open_hours": {
                "weekday": "一般 07:30 - 17:30",
                "weekend": "一般 07:30 - 17:30"
            },
            "url": "https://images.pexels.com/photos/31168964/pexels-photo-31168964.jpeg?auto=compress&cs=tinysrgb&w=1260&h=750&dpr=2"
        },
        {
            "name": "青岛栈桥",
            "description": "青岛栈桥是青岛的标志性建筑，位于青岛湾中，与小青岛隔水相望，北端与中山路成一直线相连，由海岸前伸入海，素有“长虹远引”之美誉。",
            "location": "山东省青岛市市南区太平路 12 号",
            "coordinates": {
                "latitude": 36.04072,
                "longitude": 120.33721
            },
            "rating": 4.75,
            "popularity": 85,
            "tags": [
                "海滨景观",
                "城市地标",
                "休闲散步"
            ],
            "price_range": "免费",
            "open_hours": {
                "weekday": "全天开放",
                "weekend": "全天开放"
            },
            "url": "https://images.pexels.com/photos/31168964/pexels-photo-31168964.jpeg?auto=compress&cs=tinysrgb&w=1260&h=750&dpr=2"
        },
        {
            "name": "哈尔滨中央大街",
            "description": "哈尔滨中央大街是哈尔滨最繁华的商业街，街道建筑包罗了文艺复兴，巴洛克等多种风格的建筑 71 栋，是中国国内罕见的一条建筑艺术长廊。",
            "location": "黑龙江省哈尔滨市道里区",
            "coordinates": {
                "latitude": 45.76871,
                "longitude": 126.63238
            },
            "rating": 4.82,
            "popularity": 87,
            "tags": [
                "商业街",
                "欧式建筑",
                "冰雪文化"
            ],
            "price_range": "免费",
            "open_hours": {
                "weekday": "全天开放",
                "weekend": "全天开放"
            },
            "url": "https://images.pexels.com/photos/31168964/pexels-photo-31168964.jpeg?auto=compress&cs=tinysrgb&w=1260&h=750&dpr=2"
        },
        {
            "name": "镜泊湖",
            "description": "镜泊湖是中国最大、世界第二大高山堰塞湖，以湖光山色为主，兼有火山口地下原始森林、地下熔岩隧道等地质奇观，是著名旅游、避暑和疗养胜地。",
            "location": "黑龙江省牡丹江市宁安市境西南部",
            "coordinates": {
                "latitude": 43.89003,
                "longitude": 128.82351
            },
            "rating": 4.78,
            "popularity": 83,
            "tags": [
                "堰塞湖",
                "自然景观",
                "休闲度假"
            ],
            "price_range": "门票 100 元，观光车 12 元",
            "open_hours": {
                "weekday": "08:00 - 16:00",
                "weekend": "08:00 - 16:00"
            },
            "url": "https://images.pexels.com/photos/31168964/pexels-photo-31168964.jpeg?auto=compress&cs=tinysrgb&w=1260&h=750&dpr=2"
        },
        {
            "name": "可可西里",
            "description": "可可西里是中国最大的无人区之一，也是中国海拔最高、野生动物资源最为丰富的自然保护区之一，主要保护藏羚羊、野牦牛、藏野驴、藏原羚等珍稀野生动物、植物及其栖息环境。",
            "location": "青海省玉树藏族自治州西部",
            "coordinates": {
                "latitude": 35.19367,
                "longitude": 93.46822
            },
            "rating": 4.91,
            "popularity": 86,
            "tags": [
                "无人区",
                "自然保护",
                "高原生态"
            ],
            "price_range": "免费，但需办理相关手续才能进入",
            "open_hours": {
                "weekday": "不对外开放普通游客，科研、保护等活动需申请",
                "weekend": "不对外开放普通游客，科研、保护等活动需申请"
            },
            "url": "https://images.pexels.com/photos/31168964/pexels-photo-31168964.jpeg?auto=compress&cs=tinysrgb&w=1260&h=750&dpr=2"
        },
        {
            "name": "桂林漓江",
            "description": "桂林漓江是世界上规模最大、风景最美的岩溶山水游览区之一，漓江的特点概括为清、奇、巧、变四个字，主要景点有象鼻山、九马画山、黄布倒影等。",
            "location": "广西壮族自治区桂林市灵川县、阳朔县等地",
            "coordinates": {
                "latitude": 24.91526,
                "longitude": 110.30345
            },
            "rating": 4.90,
            "popularity": 90,
            "tags": [
                "岩溶地貌",
                "山水风光",
                "游船观光"
            ],
            "price_range": "船票价格因线路和船型不同，大致在 200 - 400 元",
            "open_hours": {
                "weekday": "游船运营时间各不相同",
                "weekend": "游船运营时间各不相同"
            },
            "url": "https://images.pexels.com/photos/31168964/pexels-photo-31168964.jpeg?auto=compress&cs=tinysrgb&w=1260&h=750&dpr=2"
        }
    ]
}